aws_cost_lens/__init__.py
aws_cost_lens/__main__.py
aws_cost_lens/cli.py
aws_cost_lens/core.py
aws_cost_lens-0.1.4.dist-info/METADATA
aws_cost_lens-0.1.4.dist-info/WHEEL
aws_cost_lens-0.1.4.dist-info/entry_points.txt
aws_cost_lens-0.1.4.dist-info/licenses/LICENSE
aws_cost_lens-0.1.4.dist-info/RECORD
