Metadata-Version: 2.4
Name: aws-cost-lens
Version: 0.1.4
Summary: AWS Cost Explorer Analysis Tool
Project-URL: Homepage, https://github.com/parnell/aws-cost-lens
Project-URL: Repository, https://github.com/parnell/aws-cost-lens
Project-URL: Issues, https://github.com/parnell/aws-cost-lens/issues
License: MIT License
License-File: LICENSE
Keywords: aws,billing,cloud,cost
Classifier: Development Status :: 4 - Beta
Classifier: Environment :: Console
Classifier: Intended Audience :: Developers
Classifier: Intended Audience :: System Administrators
Classifier: License :: OSI Approved :: MIT License
Classifier: Programming Language :: Python :: 3
Classifier: Programming Language :: Python :: 3.9
Classifier: Programming Language :: Python :: 3.10
Classifier: Programming Language :: Python :: 3.11
Classifier: Programming Language :: Python :: 3.12
Classifier: Programming Language :: Python :: 3.13
Classifier: Topic :: System :: Systems Administration
Classifier: Topic :: Utilities
Requires-Python: >=3.9
Requires-Dist: boto3>=1.28.0
Requires-Dist: rich>=13.0.0
